wordlist_passphrase_generator/__init__.py
wordlist_passphrase_generator/generator.py
wordlist_passphrase_generator-0.1.data/scripts/wordlist-passphrase-generator
wordlist_passphrase_generator-0.1.dist-info/DESCRIPTION.rst
wordlist_passphrase_generator-0.1.dist-info/METADATA
wordlist_passphrase_generator-0.1.dist-info/RECORD
wordlist_passphrase_generator-0.1.dist-info/WHEEL
wordlist_passphrase_generator-0.1.dist-info/metadata.json
wordlist_passphrase_generator-0.1.dist-info/top_level.txt
