Metadata-Version: 2.0
Name: wordlist-passphrase-generator
Version: 0.1
Summary: Simple wordlist-based passphrase generator using EFF's long wordlist.
Home-page: https://github.com/rnackman/wordlist-passphrase-generator
Author: Rachel Nackman
Author-email: rachel.nackman@gmail.com
License: MIT
Platform: UNKNOWN
Classifier: Development Status :: 3 - Alpha
Classifier: Programming Language :: Python :: 2
Classifier: Topic :: Security
Requires-Dist: requests
